__init__.py
auth/__init__.py
auth/cookie_manager.py
auth/smart_auth_server.py
cli/__init__.py
cli/manual_commands.py
core/__init__.py
core/browser.py
core/config.py
core/exceptions.py
data/__init__.py
data/scheduler.py
data/storage_manager.py
data/storage/__init__.py
data/storage/base.py
data/storage/csv_storage.py
data/storage/pg_storage.py
mseep_xhs_toolkit-1.2.1.dist-info/licenses/LICENSE
server/__init__.py
server/mcp_server.py
tools/__init__.py
tools/manual_tools.py
utils/__init__.py
utils/image_processor.py
utils/logger.py
utils/text_utils.py
xiaohongshu/__init__.py
xiaohongshu/client.py
xiaohongshu/constants.py
xiaohongshu/interfaces.py
xiaohongshu/models.py
xiaohongshu/refactored_client.py
xiaohongshu/components/__init__.py
xiaohongshu/components/content_filler.py
xiaohongshu/components/data_collector.py
xiaohongshu/components/file_uploader.py
xiaohongshu/components/publisher.py
xiaohongshu/components/topic_automation.py
xiaohongshu/data_collector/__init__.py
xiaohongshu/data_collector/content_analysis.py
xiaohongshu/data_collector/dashboard.py
xiaohongshu/data_collector/fans.py
xiaohongshu/data_collector/utils.py
mseep_xhs_toolkit-1.2.1.dist-info/METADATA
mseep_xhs_toolkit-1.2.1.dist-info/WHEEL
mseep_xhs_toolkit-1.2.1.dist-info/entry_points.txt
mseep_xhs_toolkit-1.2.1.dist-info/top_level.txt
mseep_xhs_toolkit-1.2.1.dist-info/RECORD
